Workbook

Sheet Assumptions
A1: Prices | C1: Source
A2: Oil ($/bbl) | B2: 76.76 | C2: =HYPERLINK("https://www.sec.gov/ix?doc=/Archives/edgar/data/0001528129/000152812925000045/vtle-20241231.htm", "10-K SEC") -> 10-K SEC
A3: NGL ($/bbl) | B3: 13.66 | C3: =HYPERLINK("https://www.sec.gov/ix?doc=/Archives/edgar/data/0001528129/000152812925000045/vtle-20241231.htm", "10-K SEC") -> 10-K SEC
A4: Gas ($/MCF) | B4: 0.85 | C4: =HYPERLINK("https://www.sec.gov/ix?doc=/Archives/edgar/data/0001528129/000152812925000045/vtle-20241231.htm", "10-K SEC") -> 10-K SEC
E5: PV-10 Sensitivity ($MM):
E6: Oil Price (down) × Decline Multiplier (across)
A7: Product Mix | E7: ='Annual Summary'!H18 -> 3140.9468 | F7: 0.75 | G7: 1 | H7: 1.25
A8: Oil % | B8: 0.46 | C8: =HYPERLINK("https://www.sec.gov/ix?doc=/Archives/edgar/data/0001528129/000152812925000045/vtle-20241231.htm", "10-K SEC") -> 10-K SEC | E8: 55 | F8: 86.470297 | G8: -265.53606 | H8: -584.70428
A9: NGL % | B9: 0.27 | C9: =HYPERLINK("https://www.sec.gov/ix?doc=/Archives/edgar/data/0001528129/000152812925000045/vtle-20241231.htm", "10-K SEC") -> 10-K SEC | E9: 65 | F9: 1754.5935 | G9: 1299.9432 | H9: 887.70652
A10: Natural Gas % | B10: 0.27 | C10: =HYPERLINK("https://www.sec.gov/ix?doc=/Archives/edgar/data/0001528129/000152812925000045/vtle-20241231.htm", "10-K SEC") -> 10-K SEC | E10: 76.76 | F10: 3716.3065 | G10: 3140.9468 | H10: 2619.2616
E11: 85 | F11: 5090.84 | G11: 4430.9018 | H11: 3832.5281
E12: 95 | F12: 6758.9633 | G12: 5996.381 | H12: 5304.9389
A13: Costs ($/BOE)
A14: LOE (Lease operating expenses) | B14: 9.15 | C14: =HYPERLINK("https://www.sec.gov/ix?doc=/Archives/edgar/data/0001528129/000152812925000045/vtle-20241231.htm", "10-K SEC") -> 10-K SEC
A15: Production and ad valorem taxes | B15: 2.41 | C15: =HYPERLINK("https://www.sec.gov/ix?doc=/Archives/edgar/data/0001528129/000152812925000045/vtle-20241231.htm", "10-K SEC") -> 10-K SEC
A16: Oil transportation and marketing expenses | B16: 0.92 | C16: =HYPERLINK("https://www.sec.gov/ix?doc=/Archives/edgar/data/0001528129/000152812925000045/vtle-20241231.htm", "10-K SEC") -> 10-K SEC
A17: Gas gathering, processing and transportation expenses | B17: 0.36 | C17: =HYPERLINK("https://www.sec.gov/ix?doc=/Archives/edgar/data/0001528129/000152812925000045/vtle-20241231.htm", "10-K SEC") -> 10-K SEC
A18: General and administrative (excluding LTIP and transaction costs) | B18: 1.75 | C18: =HYPERLINK("https://www.sec.gov/ix?doc=/Archives/edgar/data/0001528129/000152812925000045/vtle-20241231.htm", "10-K SEC") -> 10-K SEC
A21: Capital
A22: Pads per month | B22: 1.53 | C22: Derived from budget
A23: Cost per pad ($MM) | B23: 47600000 | C23: 4 wells x $11.9 MM
A24: Drill Months | B24: 120 | C24: 10 yrs
A27: Discount
A28: Annual rate | B28: 0.1 | C28: SEC standard
A31: Decline Multiplier | B31: 1 | C31: Sensitivity dial (1.0 = base case)

Sheet DCF
A1: Month | B1: Gross BOE/d | C1: Adjusted (BOE/d) | D1: BOE / month | E1: Revenue ($) | F1: OPEX ($) | G1: EBITDA ($) | H1: CAPEX ($) | I1: Free Cash Flow ($) | J1: PV ($)
A2: 0 | B2: 143661.54 | C2: =B2 * EXP(-(Assumptions!$B$31 - 1) * 0.00421 * A2) -> 143661.54 | D2: =C2*30.4 -> 4367310.8 | E2: =D2*(Assumptions!$B$2*Assumptions!$B$8 + Assumptions!$B$3*Assumptions!$B$9 + Assumptions!$B$4*6*Assumptions!$B$10) -> 1.763293e+08 | F2: =D2*(Assumptions!$B$14+Assumptions!$B$15+Assumptions!$B$16+Assumptions!$B$17+Assumptions!$B$18) -> 63719065 | G2: =E2-F2 -> 1.1261024e+08 | H2: =IF(A2<Assumptions!$B$24, Assumptions!$B$22*Assumptions!$B$23, 0) -> 72828000 | I2: =E2-F2-H2 -> 39782236 | J2: =I2/(1+((1+Assumptions!$B$28)^(1/12)-1))^(A2+0.5) -> 39624564
A3: 1 | B3: 144650.16 | C3: =B3 * EXP(-(Assumptions!$B$31 - 1) * 0.00421 * A3) -> 144650.16 | D3: =C3*30.4 -> 4397364.9 | E3: =D3*(Assumptions!$B$2*Assumptions!$B$8 + Assumptions!$B$3*Assumptions!$B$9 + Assumptions!$B$4*6*Assumptions!$B$10) -> 1.7754273e+08 | F3: =D3*(Assumptions!$B$14+Assumptions!$B$15+Assumptions!$B$16+Assumptions!$B$17+Assumptions!$B$18) -> 64157554 | G3: =E3-F3 -> 1.1338517e+08 | H3: =IF(A3<Assumptions!$B$24, Assumptions!$B$22*Assumptions!$B$23, 0) -> 72828000 | I3: =E3-F3-H3 -> 40557174 | J3: =I3/(1+((1+Assumptions!$B$28)^(1/12)-1))^(A3+0.5) -> 40076852
A4: 2 | B4: 145023.5 | C4: =B4 * EXP(-(Assumptions!$B$31 - 1) * 0.00421 * A4) -> 145023.5 | D4: =C4*30.4 -> 4408714.3 | E4: =D4*(Assumptions!$B$2*Assumptions!$B$8 + Assumptions!$B$3*Assumptions!$B$9 + Assumptions!$B$4*6*Assumptions!$B$10) -> 1.7800096e+08 | F4: =D4*(Assumptions!$B$14+Assumptions!$B$15+Assumptions!$B$16+Assumptions!$B$17+Assumptions!$B$18) -> 64323142 | G4: =E4-F4 -> 1.1367782e+08 | H4: =IF(A4<Assumptions!$B$24, Assumptions!$B$22*Assumptions!$B$23, 0) -> 72828000 | I4: =E4-F4-H4 -> 40849817 | J4: =I4/(1+((1+Assumptions!$B$28)^(1/12)-1))^(A4+0.5) -> 40046692
A5: 3 | B5: 145020.54 | C5: =B5 * EXP(-(Assumptions!$B$31 - 1) * 0.00421 * A5) -> 145020.54 | D5: =C5*30.4 -> 4408624.4 | E5: =D5*(Assumptions!$B$2*Assumptions!$B$8 + Assumptions!$B$3*Assumptions!$B$9 + Assumptions!$B$4*6*Assumptions!$B$10) -> 1.7799733e+08 | F5: =D5*(Assumptions!$B$14+Assumptions!$B$15+Assumptions!$B$16+Assumptions!$B$17+Assumptions!$B$18) -> 64321830 | G5: =E5-F5 -> 1.136755e+08 | H5: =IF(A5<Assumptions!$B$24, Assumptions!$B$22*Assumptions!$B$23, 0) -> 72828000 | I5: =E5-F5-H5 -> 40847499 | J5: =I5/(1+((1+Assumptions!$B$28)^(1/12)-1))^(A5+0.5) -> 39727625
A6: 4 | B6: 144775.13 | C6: =B6 * EXP(-(Assumptions!$B$31 - 1) * 0.00421 * A6) -> 144775.13 | D6: =C6*30.4 -> 4401163.9 | E6: =D6*(Assumptions!$B$2*Assumptions!$B$8 + Assumptions!$B$3*Assumptions!$B$9 + Assumptions!$B$4*6*Assumptions!$B$10) -> 1.7769611e+08 | F6: =D6*(Assumptions!$B$14+Assumptions!$B$15+Assumptions!$B$16+Assumptions!$B$17+Assumptions!$B$18) -> 64212981 | G6: =E6-F6 -> 1.1348313e+08 | H6: =IF(A6<Assumptions!$B$24, Assumptions!$B$22*Assumptions!$B$23, 0) -> 72828000 | I6: =E6-F6-H6 -> 40655131 | J6: =I6/(1+((1+Assumptions!$B$28)^(1/12)-1))^(A6+0.5) -> 39227723
A7: 5 | B7: 144368.99 | C7: =B7 * EXP(-(Assumptions!$B$31 - 1) * 0.00421 * A7) -> 144368.99 | D7: =C7*30.4 -> 4388817.2 | E7: =D7*(Assumptions!$B$2*Assumptions!$B$8 + Assumptions!$B$3*Assumptions!$B$9 + Assumptions!$B$4*6*Assumptions!$B$10) -> 1.7719762e+08 | F7: =D7*(Assumptions!$B$14+Assumptions!$B$15+Assumptions!$B$16+Assumptions!$B$17+Assumptions!$B$18) -> 64032842 | G7: =E7-F7 -> 1.1316477e+08 | H7: =IF(A7<Assumptions!$B$24, Assumptions!$B$22*Assumptions!$B$23, 0) -> 72828000 | I7: =E7-F7-H7 -> 40336773 | J7: =I7/(1+((1+Assumptions!$B$28)^(1/12)-1))^(A7+0.5) -> 38612641
A8: 6 | B8: 143855 | C8: =B8 * EXP(-(Assumptions!$B$31 - 1) * 0.00421 * A8) -> 143855 | D8: =C8*30.4 -> 4373192.1 | E8: =D8*(Assumptions!$B$2*Assumptions!$B$8 + Assumptions!$B$3*Assumptions!$B$9 + Assumptions!$B$4*6*Assumptions!$B$10) -> 1.7656676e+08 | F8: =D8*(Assumptions!$B$14+Assumptions!$B$15+Assumptions!$B$16+Assumptions!$B$17+Assumptions!$B$18) -> 63804873 | G8: =E8-F8 -> 1.1276188e+08 | H8: =IF(A8<Assumptions!$B$24, Assumptions!$B$22*Assumptions!$B$23, 0) -> 72828000 | I8: =E8-F8-H8 -> 39933884 | J8: =I8/(1+((1+Assumptions!$B$28)^(1/12)-1))^(A8+0.5) -> 37924557
A9: 7 | B9: 143268.86 | C9: =B9 * EXP(-(Assumptions!$B$31 - 1) * 0.00421 * A9) -> 143268.86 | D9: =C9*30.4 -> 4355373.2 | E9: =D9*(Assumptions!$B$2*Assumptions!$B$8 + Assumptions!$B$3*Assumptions!$B$9 + Assumptions!$B$4*6*Assumptions!$B$10) -> 1.7584732e+08 | F9: =D9*(Assumptions!$B$14+Assumptions!$B$15+Assumptions!$B$16+Assumptions!$B$17+Assumptions!$B$18) -> 63544895 | G9: =E9-F9 -> 1.1230243e+08 | H9: =IF(A9<Assumptions!$B$24, Assumptions!$B$22*Assumptions!$B$23, 0) -> 72828000 | I9: =E9-F9-H9 -> 39474427 | J9: =I9/(1+((1+Assumptions!$B$28)^(1/12)-1))^(A9+0.5) -> 37191647
A10: 8 | B10: 142635.33 | C10: =B10 * EXP(-(Assumptions!$B$31 - 1) * 0.00421 * A10) -> 142635.33 | D10: =C10*30.4 -> 4336114.2 | E10: =D10*(Assumptions!$B$2*Assumptions!$B$8 + Assumptions!$B$3*Assumptions!$B$9 + Assumptions!$B$4*6*Assumptions!$B$10) -> 1.7506974e+08 | F10: =D10*(Assumptions!$B$14+Assumptions!$B$15+Assumptions!$B$16+Assumptions!$B$17+Assumptions!$B$18) -> 63263906 | G10: =E10-F10 -> 1.1180584e+08 | H10: =IF(A10<Assumptions!$B$24, Assumptions!$B$22*Assumptions!$B$23, 0) -> 72828000 | I10: =E10-F10-H10 -> 38977837 | J10: =I10/(1+((1+Assumptions!$B$28)^(1/12)-1))^(A10+0.5) -> 36433250
A11: 9 | B11: 141972.07 | C11: =B11 * EXP(-(Assumptions!$B$31 - 1) * 0.00421 * A11) -> 141972.07 | D11: =C11*30.4 -> 4315950.8 | E11: =D11*(Assumptions!$B$2*Assumptions!$B$8 + Assumptions!$B$3*Assumptions!$B$9 + Assumptions!$B$4*6*Assumptions!$B$10) -> 1.7425565e+08 | F11: =D11*(Assumptions!$B$14+Assumptions!$B$15+Assumptions!$B$16+Assumptions!$B$17+Assumptions!$B$18) -> 62969722 | G11: =E11-F11 -> 1.1128593e+08 | H11: =IF(A11<Assumptions!$B$24, Assumptions!$B$22*Assumptions!$B$23, 0) -> 72828000 | I11: =E11-F11-H11 -> 38457928 | J11: =I11/(1+((1+Assumptions!$B$28)^(1/12)-1))^(A11+0.5) -> 35662902
A12: 10 | B12: 141291.78 | C12: =B12 * EXP(-(Assumptions!$B$31 - 1) * 0.00421 * A12) -> 141291.78 | D12: =C12*30.4 -> 4295270.2 | E12: =D12*(Assumptions!$B$2*Assumptions!$B$8 + Assumptions!$B$3*Assumptions!$B$9 + Assumptions!$B$4*6*Assumptions!$B$10) -> 1.7342068e+08 | F12: =D12*(Assumptions!$B$14+Assumptions!$B$15+Assumptions!$B$16+Assumptions!$B$17+Assumptions!$B$18) -> 62667992 | G12: =E12-F12 -> 1.1075268e+08 | H12: =IF(A12<Assumptions!$B$24, Assumptions!$B$22*Assumptions!$B$23, 0) -> 72828000 | I12: =E12-F12-H12 -> 37924683 | J12: =I12/(1+((1+Assumptions!$B$28)^(1/12)-1))^(A12+0.5) -> 34890192
A13: 11 | B13: 140603.8 | C13: =B13 * EXP(-(Assumptions!$B$31 - 1) * 0.00421 * A13) -> 140603.8 | D13: =C13*30.4 -> 4274355.4 | E13: =D13*(Assumptions!$B$2*Assumptions!$B$8 + Assumptions!$B$3*Assumptions!$B$9 + Assumptions!$B$4*6*Assumptions!$B$10) -> 1.7257624e+08 | F13: =D13*(Assumptions!$B$14+Assumptions!$B$15+Assumptions!$B$16+Assumptions!$B$17+Assumptions!$B$18) -> 62362845 | G13: =E13-F13 -> 1.102134e+08 | H13: =IF(A13<Assumptions!$B$24, Assumptions!$B$22*Assumptions!$B$23, 0) -> 72828000 | I13: =E13-F13-H13 -> 37385398 | J13: =I13/(1+((1+Assumptions!$B$28)^(1/12)-1))^(A13+0.5) -> 34121964
... A181: 179 | B181: 50860.488 | C181: =B181 * EXP(-(Assumptions!$B$31 - 1) * 0.00421 * A181) -> 50860.488 | D181: =C181*30.4 -> 1546158.8 | E181: =D181*(Assumptions!$B$2*Assumptions!$B$8 + Assumptions!$B$3*Assumptions!$B$9 + Assumptions!$B$4*6*Assumptions!$B$10) -> 62425854 | F181: =D181*(Assumptions!$B$14+Assumptions!$B$15+Assumptions!$B$16+Assumptions!$B$17+Assumptions!$B$18) -> 22558457 | G181: =E181-F181 -> 39867396 | H181: =IF(A181<Assumptions!$B$24, Assumptions!$B$22*Assumptions!$B$23, 0) -> 0 | I181: =E181-F181-H181 -> 39867396 | J181: =I181/(1+((1+Assumptions!$B$28)^(1/12)-1))^(A181+0.5) -> 9581914.5
A183: Total | B183: =SUM(B2:B181) -> 19254139 | C183: =SUM(C2:C181) -> 19254139 | D183: =SUM(D2:D181) -> 5.8532583e+08 | E183: =SUM(E2:E181) -> 2.3632413e+10 | F183: =SUM(F2:F181) -> 8.5399038e+09 | G183: =SUM(G2:G181) -> 1.5092509e+10 | H183: =SUM(H2:H181) -> 8739360000 | I183: =SUM(I2:I181) -> 6.3531494e+09 | J183: =SUM(J2:J181) -> 3.1409468e+09

Sheet Annual Summary
A1: Year | B1: Production (MBOE) | C1: Revenue ($MM) | D1: OPEX ($MM) | E1: EBITDA ($MM) | F1: CAPEX ($MM) | G1: Free Cash Flow ($MM) | H1: PV ($MM)
A2: 1 | B2: =SUMIFS(DCF!D:D, DCF!A:A, ">="&(A2-1)*12, DCF!A:A, "<"&A2*12) / 1000 -> 52322.251 | C2: =SUMIFS(DCF!E:E, DCF!A:A, ">="&(A2-1)*12, DCF!A:A, "<"&A2*12) / 1000000 -> 2112.5004 | D2: =SUMIFS(DCF!F:F, DCF!A:A, ">="&(A2-1)*12, DCF!A:A, "<"&A2*12) / 1000000 -> 763.38165 | E2: =C2-D2 -> 1349.1188 | F2: =SUMIFS(DCF!H:H, DCF!A:A, ">="&(A2-1)*12, DCF!A:A, "<"&A2*12) / 1000000 -> 873.936 | G2: =SUMIFS(DCF!I:I, DCF!A:A, ">="&(A2-1)*12, DCF!A:A, "<"&A2*12) / 1000000 -> 475.18279 | H2: =SUMIFS(DCF!J:J, DCF!A:A, ">="&(A2-1)*12, DCF!A:A, "<"&A2*12) / 1000000 -> 453.54061
A3: 2 | B3: =SUMIFS(DCF!D:D, DCF!A:A, ">="&(A3-1)*12, DCF!A:A, "<"&A3*12) / 1000 -> 49748.271 | C3: =SUMIFS(DCF!E:E, DCF!A:A, ">="&(A3-1)*12, DCF!A:A, "<"&A3*12) / 1000000 -> 2008.5765 | D3: =SUMIFS(DCF!F:F, DCF!A:A, ">="&(A3-1)*12, DCF!A:A, "<"&A3*12) / 1000000 -> 725.82727 | E3: =C3-D3 -> 1282.7492 | F3: =SUMIFS(DCF!H:H, DCF!A:A, ">="&(A3-1)*12, DCF!A:A, "<"&A3*12) / 1000000 -> 873.936 | G3: =SUMIFS(DCF!I:I, DCF!A:A, ">="&(A3-1)*12, DCF!A:A, "<"&A3*12) / 1000000 -> 408.81321 | H3: =SUMIFS(DCF!J:J, DCF!A:A, ">="&(A3-1)*12, DCF!A:A, "<"&A3*12) / 1000000 -> 354.96568
A4: 3 | B4: =SUMIFS(DCF!D:D, DCF!A:A, ">="&(A4-1)*12, DCF!A:A, "<"&A4*12) / 1000 -> 47438.646 | C4: =SUMIFS(DCF!E:E, DCF!A:A, ">="&(A4-1)*12, DCF!A:A, "<"&A4*12) / 1000000 -> 1915.3259 | D4: =SUMIFS(DCF!F:F, DCF!A:A, ">="&(A4-1)*12, DCF!A:A, "<"&A4*12) / 1000000 -> 692.12985 | E4: =C4-D4 -> 1223.196 | F4: =SUMIFS(DCF!H:H, DCF!A:A, ">="&(A4-1)*12, DCF!A:A, "<"&A4*12) / 1000000 -> 873.936 | G4: =SUMIFS(DCF!I:I, DCF!A:A, ">="&(A4-1)*12, DCF!A:A, "<"&A4*12) / 1000000 -> 349.26 | H4: =SUMIFS(DCF!J:J, DCF!A:A, ">="&(A4-1)*12, DCF!A:A, "<"&A4*12) / 1000000 -> 275.62135
A5: 4 | B5: =SUMIFS(DCF!D:D, DCF!A:A, ">="&(A5-1)*12, DCF!A:A, "<"&A5*12) / 1000 -> 45857.269 | C5: =SUMIFS(DCF!E:E, DCF!A:A, ">="&(A5-1)*12, DCF!A:A, "<"&A5*12) / 1000000 -> 1851.4781 | D5: =SUMIFS(DCF!F:F, DCF!A:A, ">="&(A5-1)*12, DCF!A:A, "<"&A5*12) / 1000000 -> 669.05756 | E5: =C5-D5 -> 1182.4205 | F5: =SUMIFS(DCF!H:H, DCF!A:A, ">="&(A5-1)*12, DCF!A:A, "<"&A5*12) / 1000000 -> 873.936 | G5: =SUMIFS(DCF!I:I, DCF!A:A, ">="&(A5-1)*12, DCF!A:A, "<"&A5*12) / 1000000 -> 308.48452 | H5: =SUMIFS(DCF!J:J, DCF!A:A, ">="&(A5-1)*12, DCF!A:A, "<"&A5*12) / 1000000 -> 221.25358
A6: 5 | B6: =SUMIFS(DCF!D:D, DCF!A:A, ">="&(A6-1)*12, DCF!A:A, "<"&A6*12) / 1000 -> 44794.019 | C6: =SUMIFS(DCF!E:E, DCF!A:A, ">="&(A6-1)*12, DCF!A:A, "<"&A6*12) / 1000000 -> 1808.5496 | D6: =SUMIFS(DCF!F:F, DCF!A:A, ">="&(A6-1)*12, DCF!A:A, "<"&A6*12) / 1000000 -> 653.54474 | E6: =C6-D6 -> 1155.0048 | F6: =SUMIFS(DCF!H:H, DCF!A:A, ">="&(A6-1)*12, DCF!A:A, "<"&A6*12) / 1000000 -> 873.936 | G6: =SUMIFS(DCF!I:I, DCF!A:A, ">="&(A6-1)*12, DCF!A:A, "<"&A6*12) / 1000000 -> 281.06882 | H6: =SUMIFS(DCF!J:J, DCF!A:A, ">="&(A6-1)*12, DCF!A:A, "<"&A6*12) / 1000000 -> 183.223
A7: 6 | B7: =SUMIFS(DCF!D:D, DCF!A:A, ">="&(A7-1)*12, DCF!A:A, "<"&A7*12) / 1000 -> 44082.588 | C7: =SUMIFS(DCF!E:E, DCF!A:A, ">="&(A7-1)*12, DCF!A:A, "<"&A7*12) / 1000000 -> 1779.8257 | D7: =SUMIFS(DCF!F:F, DCF!A:A, ">="&(A7-1)*12, DCF!A:A, "<"&A7*12) / 1000000 -> 643.16495 | E7: =C7-D7 -> 1136.6607 | F7: =SUMIFS(DCF!H:H, DCF!A:A, ">="&(A7-1)*12, DCF!A:A, "<"&A7*12) / 1000000 -> 873.936 | G7: =SUMIFS(DCF!I:I, DCF!A:A, ">="&(A7-1)*12, DCF!A:A, "<"&A7*12) / 1000000 -> 262.72471 | H7: =SUMIFS(DCF!J:J, DCF!A:A, ">="&(A7-1)*12, DCF!A:A, "<"&A7*12) / 1000000 -> 155.66733
A8: 7 | B8: =SUMIFS(DCF!D:D, DCF!A:A, ">="&(A8-1)*12, DCF!A:A, "<"&A8*12) / 1000 -> 43613.613 | C8: =SUMIFS(DCF!E:E, DCF!A:A, ">="&(A8-1)*12, DCF!A:A, "<"&A8*12) / 1000000 -> 1760.8909 | D8: =SUMIFS(DCF!F:F, DCF!A:A, ">="&(A8-1)*12, DCF!A:A, "<"&A8*12) / 1000000 -> 636.32261 | E8: =C8-D8 -> 1124.5683 | F8: =SUMIFS(DCF!H:H, DCF!A:A, ">="&(A8-1)*12, DCF!A:A, "<"&A8*12) / 1000000 -> 873.936 | G8: =SUMIFS(DCF!I:I, DCF!A:A, ">="&(A8-1)*12, DCF!A:A, "<"&A8*12) / 1000000 -> 250.63228 | H8: =SUMIFS(DCF!J:J, DCF!A:A, ">="&(A8-1)*12, DCF!A:A, "<"&A8*12) / 1000000 -> 134.98306
A9: 8 | B9: =SUMIFS(DCF!D:D, DCF!A:A, ">="&(A9-1)*12, DCF!A:A, "<"&A9*12) / 1000 -> 43306.154 | C9: =SUMIFS(DCF!E:E, DCF!A:A, ">="&(A9-1)*12, DCF!A:A, "<"&A9*12) / 1000000 -> 1748.4773 | D9: =SUMIFS(DCF!F:F, DCF!A:A, ">="&(A9-1)*12, DCF!A:A, "<"&A9*12) / 1000000 -> 631.83679 | E9: =C9-D9 -> 1116.6405 | F9: =SUMIFS(DCF!H:H, DCF!A:A, ">="&(A9-1)*12, DCF!A:A, "<"&A9*12) / 1000000 -> 873.936 | G9: =SUMIFS(DCF!I:I, DCF!A:A, ">="&(A9-1)*12, DCF!A:A, "<"&A9*12) / 1000000 -> 242.70452 | H9: =SUMIFS(DCF!J:J, DCF!A:A, ">="&(A9-1)*12, DCF!A:A, "<"&A9*12) / 1000000 -> 118.82036
A10: 9 | B10: =SUMIFS(DCF!D:D, DCF!A:A, ">="&(A10-1)*12, DCF!A:A, "<"&A10*12) / 1000 -> 43065.711 | C10: =SUMIFS(DCF!E:E, DCF!A:A, ">="&(A10-1)*12, DCF!A:A, "<"&A10*12) / 1000000 -> 1738.7695 | D10: =SUMIFS(DCF!F:F, DCF!A:A, ">="&(A10-1)*12, DCF!A:A, "<"&A10*12) / 1000000 -> 628.32872 | E10: =C10-D10 -> 1110.4407 | F10: =SUMIFS(DCF!H:H, DCF!A:A, ">="&(A10-1)*12, DCF!A:A, "<"&A10*12) / 1000000 -> 873.936 | G10: =SUMIFS(DCF!I:I, DCF!A:A, ">="&(A10-1)*12, DCF!A:A, "<"&A10*12) / 1000000 -> 236.50474 | H10: =SUMIFS(DCF!J:J, DCF!A:A, ">="&(A10-1)*12, DCF!A:A, "<"&A10*12) / 1000000 -> 105.25617
A11: 10 | B11: =SUMIFS(DCF!D:D, DCF!A:A, ">="&(A11-1)*12, DCF!A:A, "<"&A11*12) / 1000 -> 42863.408 | C11: =SUMIFS(DCF!E:E, DCF!A:A, ">="&(A11-1)*12, DCF!A:A, "<"&A11*12) / 1000000 -> 1730.6015 | D11: =SUMIFS(DCF!F:F, DCF!A:A, ">="&(A11-1)*12, DCF!A:A, "<"&A11*12) / 1000000 -> 625.37713 | E11: =C11-D11 -> 1105.2244 | F11: =SUMIFS(DCF!H:H, DCF!A:A, ">="&(A11-1)*12, DCF!A:A, "<"&A11*12) / 1000000 -> 873.936 | G11: =SUMIFS(DCF!I:I, DCF!A:A, ">="&(A11-1)*12, DCF!A:A, "<"&A11*12) / 1000000 -> 231.28841 | H11: =SUMIFS(DCF!J:J, DCF!A:A, ">="&(A11-1)*12, DCF!A:A, "<"&A11*12) / 1000000 -> 93.574559
A12: 11 | B12: =SUMIFS(DCF!D:D, DCF!A:A, ">="&(A12-1)*12, DCF!A:A, "<"&A12*12) / 1000 -> 34889.746 | C12: =SUMIFS(DCF!E:E, DCF!A:A, ">="&(A12-1)*12, DCF!A:A, "<"&A12*12) / 1000000 -> 1408.6665 | D12: =SUMIFS(DCF!F:F, DCF!A:A, ">="&(A12-1)*12, DCF!A:A, "<"&A12*12) / 1000000 -> 509.04139 | E12: =C12-D12 -> 899.62511 | F12: =SUMIFS(DCF!H:H, DCF!A:A, ">="&(A12-1)*12, DCF!A:A, "<"&A12*12) / 1000000 -> 0 | G12: =SUMIFS(DCF!I:I, DCF!A:A, ">="&(A12-1)*12, DCF!A:A, "<"&A12*12) / 1000000 -> 899.62511 | H12: =SUMIFS(DCF!J:J, DCF!A:A, ">="&(A12-1)*12, DCF!A:A, "<"&A12*12) / 1000000 -> 331.60158
A13: 12 | B13: =SUMIFS(DCF!D:D, DCF!A:A, ">="&(A13-1)*12, DCF!A:A, "<"&A13*12) / 1000 -> 28067.44 | C13: =SUMIFS(DCF!E:E, DCF!A:A, ">="&(A13-1)*12, DCF!A:A, "<"&A13*12) / 1000000 -> 1133.2173 | D13: =SUMIFS(DCF!F:F, DCF!A:A, ">="&(A13-1)*12, DCF!A:A, "<"&A13*12) / 1000000 -> 409.50394 | E13: =C13-D13 -> 723.71332 | F13: =SUMIFS(DCF!H:H, DCF!A:A, ">="&(A13-1)*12, DCF!A:A, "<"&A13*12) / 1000000 -> 0 | G13: =SUMIFS(DCF!I:I, DCF!A:A, ">="&(A13-1)*12, DCF!A:A, "<"&A13*12) / 1000000 -> 723.71332 | H13: =SUMIFS(DCF!J:J, DCF!A:A, ">="&(A13-1)*12, DCF!A:A, "<"&A13*12) / 1000000 -> 242.25822
... A16: 15 | B16: =SUMIFS(DCF!D:D, DCF!A:A, ">="&(A16-1)*12, DCF!A:A, "<"&A16*12) / 1000 -> 19421.883 | C16: =SUMIFS(DCF!E:E, DCF!A:A, ">="&(A16-1)*12, DCF!A:A, "<"&A16*12) / 1000000 -> 784.15462 | D16: =SUMIFS(DCF!F:F, DCF!A:A, ">="&(A16-1)*12, DCF!A:A, "<"&A16*12) / 1000000 -> 283.36527 | E16: =C16-D16 -> 500.78936 | F16: =SUMIFS(DCF!H:H, DCF!A:A, ">="&(A16-1)*12, DCF!A:A, "<"&A16*12) / 1000000 -> 0 | G16: =SUMIFS(DCF!I:I, DCF!A:A, ">="&(A16-1)*12, DCF!A:A, "<"&A16*12) / 1000000 -> 500.78936 | H16: =SUMIFS(DCF!J:J, DCF!A:A, ">="&(A16-1)*12, DCF!A:A, "<"&A16*12) / 1000000 -> 125.88287
A18: Total | B18: =SUM(B2:B16) -> 585325.83 | C18: =SUM(C2:C16) -> 23632.413 | D18: =SUM(D2:D16) -> 8539.9038 | E18: =SUM(E2:E16) -> 15092.509 | F18: =SUM(F2:F16) -> 8739.36 | G18: =SUM(G2:G16) -> 6353.1494 | H18: =SUM(H2:H16) -> 3140.9468
